testcloud/__init__.py
testcloud/cli.py
testcloud/config.py
testcloud/domain_configuration.py
testcloud/exceptions.py
testcloud/image.py
testcloud/instance.py
testcloud/sql.py
testcloud/util.py
testcloud/workarounds.py
testcloud/distro_utils/__init__.py
testcloud/distro_utils/alma.py
testcloud/distro_utils/centos.py
testcloud/distro_utils/debian.py
testcloud/distro_utils/fedora.py
testcloud/distro_utils/misc.py
testcloud/distro_utils/oracle.py
testcloud/distro_utils/rocky.py
testcloud/distro_utils/ubuntu.py
testcloud-0.11.8.data/data/share/bash-completion/completions/testcloud
testcloud-0.11.8.data/data/share/man/man1/testcloud.1
testcloud-0.11.8.dist-info/LICENSE
testcloud-0.11.8.dist-info/METADATA
testcloud-0.11.8.dist-info/WHEEL
testcloud-0.11.8.dist-info/entry_points.txt
testcloud-0.11.8.dist-info/top_level.txt
testcloud-0.11.8.dist-info/RECORD
