Metadata-Version: 2.1
Name: testcloud
Version: 0.11.8
Summary: A tool to download and boot cloud images locally, with an easy to use API.
Home-page: https://pagure.io/testcloud
Author: Mike Ruckman
Author-email: roshi@fedoraproject.org
License: GPLv2+
License-File: LICENSE
Requires-Dist: libvirt-python
Requires-Dist: peewee
Requires-Dist: requests
Requires-Dist: packaging
Provides-Extra: image_resolve_caching
Requires-Dist: requests-cache >=1.2 ; extra == 'image_resolve_caching'
